ndr_core/VERSION
ndr_core/__init__.py
ndr_core/admin.py
ndr_core/admin_tables.py
ndr_core/api_factory.py
ndr_core/apps.py
ndr_core/exceptions.py
ndr_core/form_preview.py
ndr_core/geo_ip_utils.py
ndr_core/models.py
ndr_core/ndr_helpers.py
ndr_core/ndr_settings.py
ndr_core/ndr_template_tags.py
ndr_core/prog_stats.py
ndr_core/urls.py
ndr_core/utils.py
ndr_core/views.py
ndr_core/admin_forms/__init__.py
ndr_core/admin_forms/admin_forms.py
ndr_core/admin_forms/color_forms.py
ndr_core/admin_forms/images_forms.py
ndr_core/admin_forms/page_forms.py
ndr_core/admin_forms/result_card_forms.py
ndr_core/admin_forms/result_field_forms.py
ndr_core/admin_forms/search_config_forms.py
ndr_core/admin_forms/search_field_forms.py
ndr_core/admin_forms/search_form_forms.py
ndr_core/admin_forms/settings_forms.py
ndr_core/admin_forms/translation_forms.py
ndr_core/admin_forms/ui_element_forms.py
ndr_core/admin_forms/upload_forms.py
ndr_core/admin_views/__init__.py
ndr_core/admin_views/admin_views.py
ndr_core/admin_views/color_views.py
ndr_core/admin_views/corrections_views.py
ndr_core/admin_views/export_views.py
ndr_core/admin_views/images_views.py
ndr_core/admin_views/messages_views.py
ndr_core/admin_views/page_views.py
ndr_core/admin_views/result_views.py
ndr_core/admin_views/search_field_views.py
ndr_core/admin_views/search_views.py
ndr_core/admin_views/seo_views.py
ndr_core/admin_views/settings_views.py
ndr_core/admin_views/translation_views.py
ndr_core/admin_views/ui_element_views.py
ndr_core/admin_views/ui_style_views.py
ndr_core/admin_views/uploads_views.py
ndr_core/api/__init__.py
ndr_core/api/base_query.py
ndr_core/api/base_result.py
ndr_core/api/api_ninjas/__init__.py
ndr_core/api/api_ninjas/api_ninjas_query.py
ndr_core/api/api_ninjas/api_ninjas_result.py
ndr_core/api/mongodb/__init__.py
ndr_core/api/mongodb/mongodb_query.py
ndr_core/api/mongodb/mongodb_result.py
ndr_core/api/ndr_core/field_configuration.py
ndr_core/api/ndr_core/ndr_core_query.py
django_ndr_core-0.42.0.dist-info/LICENSE
django_ndr_core-0.42.0.dist-info/METADATA
django_ndr_core-0.42.0.dist-info/WHEEL
django_ndr_core-0.42.0.dist-info/top_level.txt
django_ndr_core-0.42.0.dist-info/RECORD
