Metadata-Version: 2.1
Name: django-ndr-core
Version: 0.42.0
Summary: A Django app to search and view data from an API.
Home-page: https://django-ndr-core.readthedocs.io/en/latest/
Author: Sorin Marti
Author-email: sorin.marti@gmail.com
License: MIT License
Classifier: Development Status :: 3 - Alpha
Classifier: Environment :: Web Environment
Classifier: Framework :: Django
Classifier: Framework :: Django :: 4.2
Classifier: Intended Audience :: Developers
Classifier: License :: OSI Approved :: MIT License
Classifier: Natural Language :: English
Classifier: Operating System :: OS Independent
Classifier: Programming Language :: Python
Classifier: Programming Language :: Python :: 3
Classifier: Programming Language :: Python :: 3 :: Only
Classifier: Programming Language :: Python :: 3.9
Classifier: Programming Language :: Python :: 3.11
Classifier: Topic :: Internet :: WWW/HTTP
Classifier: Topic :: Internet :: WWW/HTTP :: Dynamic Content
Classifier: Topic :: Database
Classifier: Topic :: Database :: Front-Ends
Requires-Python: >=3.9
License-File: LICENSE
Requires-Dist: requests ~=2.31.0
Requires-Dist: Django ~=5.0.4
Requires-Dist: django-bootstrap4 ==23.1
Requires-Dist: django-crispy-forms ==2.0
Requires-Dist: django-tables2 ==2.5.3
Requires-Dist: django-select2 ==8.1.1
Requires-Dist: django-ckeditor ~=6.5.1
Requires-Dist: django-recaptcha ~=3.0.0
Requires-Dist: django-colorfield ~=0.8.0
Requires-Dist: fontawesomefree ==6.4.0
Requires-Dist: Pillow ==10.2.0
Requires-Dist: geoip2 ~=4.6.0
Requires-Dist: pymongo ~=4.3
Requires-Dist: crispy-bootstrap4 >=2022.1
Requires-Dist: django-bootstrap-daterangepicker ~=1.1.0
Requires-Dist: pandas ==2.2.1
Requires-Dist: setuptools ==67.7.2
Requires-Dist: sphinx ==6.2.1
Requires-Dist: sphinx-rtd-theme ==1.2.0
Requires-Dist: readthedocs-sphinx-search ==0.3.2
Requires-Dist: django-filter ==23.1
